74LVC161/x74161.v
module x74161(
    CR,PE,CEP,CET,CP,D, Q,TC
);

input CR,PE,CEP,CET,CP;
input [3:0]D;
output reg [3:0]Q;
output reg TC;

always @(posedge CP or negedge CR)
begin
if (~CR)begin   
        Q <= 4'b1111;
        TC <= 0;
    end
    
else if (~PE)
    Q <= D;

else
    casex ({CEP,CET})
	2'b0x: Q <= Q;         //保持
	2'bx0:begin 
        Q <= Q; TC <= 0; 
        end      //保持
	2'b11:begin 
        Q<=Q+1'b1; TC<=(Q==4'b1111); 
        end    //计数
    endcase
end

endmodule

74LVC161/x74161_tb.v
//~ `New testbench
`timescale  1ns / 1ps
`include "x74161.v"
module tb_x74161;

// x74161 Inputs
reg   CR                                   = 0 ;
reg   PE                                   = 0 ;
reg   CEP                                  = 0 ;
reg   CET                                  = 0 ;
reg   CP                                   = 0 ;
reg   [3:0]  D                             = 0 ;

// x74161 Outputs
wire  [3:0]  Q                             ;
wire  TC                                   ;

x74161  u_x74161 (
    .CR                      ( CR         ),
    .PE                      ( PE         ),
    .CEP                     ( CEP        ),
    .CET                     ( CET        ),
    .CP                      ( CP         ),
    .D                       ( D    [3:0] ),

    .Q                       ( Q    [3:0] ),
    .TC                      ( TC         )
);

initial
	$monitor($time,"\tCR=%b,PE=%b,CEP=%b,CET=%b,CP=%b,D=%b,Q=%b,TC=%b",CR,PE,CEP,CET,CP,D,Q,TC);
//时钟信号
initial
    CP=1;
always 
    #5 CP=~CP;
//元件例化    
initial
begin
    $dumpfile("x74161.vcd");
    $dumpvars(0,u_x74161,CR,PE,CEP,CET,CP,D,Q,TC);
    //清零
	CR=0;PE=1;D=4'b1100;CET=0;CEP=0;
	#5;
	//置数
	CR=1;PE=0;D=4'b1100;CET=0;CEP=0;
	#10;
	//计数
	CR=1;PE=1;D=4'b0000;CET=1;CEP=1;
	#60;
	//禁止计数
	CR=1;PE=1;D=4'b0000;CET=1;CEP=0;
	#20;
    $finish;
end

endmodule

74LVC161/x74161.vcd
$date
	Wed Dec 20 21:59:06 2023
$end
$version
	Icarus Verilog
$end
$timescale
	1ps
$end
$scope module tb_x74161 $end
$scope module u_x74161 $end
$var wire 1 ! CEP $end
$var wire 1 " CET $end
$var wire 1 # CP $end
$var wire 1 $ CR $end
$var wire 4 % D [3:0] $end
$var wire 1 & PE $end
$var reg 4 ' Q [3:0] $end
$var reg 1 ( TC $end
$upscope $end
$upscope $end
$scope module tb_x74161 $end
$var reg 1 $ CR $end
$upscope $end
$scope module tb_x74161 $end
$var reg 1 & PE $end
$upscope $end
$scope module tb_x74161 $end
$var reg 1 ! CEP $end
$upscope $end
$scope module tb_x74161 $end
$var reg 1 " CET $end
$upscope $end
$scope module tb_x74161 $end
$var reg 1 # CP $end
$upscope $end
$scope module tb_x74161 $end
$var reg 4 ) D [3:0] $end
$upscope $end
$scope module tb_x74161 $end
$var wire 4 * Q [3:0] $end
$upscope $end
$scope module tb_x74161 $end
$var wire 1 ( TC $end
$upscope $end
$enddefinitions $end
$comment Show the parameter values. $end
$dumpall
$end
#0
$dumpvars
b1111 *
b1100 )
0(
b1111 '
1&
b1100 %
0$
1#
0"
0!
$end
#5000
0&
1$
0#
#10000
b1100 '
b1100 *
1#
#15000
0#
1!
1"
b0 %
b0 )
1&
#20000
b1101 '
b1101 *
1#
#25000
0#
#30000
b1110 '
b1110 *
1#
#35000
0#
#40000
b1111 '
b1111 *
1#
#45000
0#
#50000
1(
b0 '
b0 *
1#
#55000
0#
#60000
0(
b1 '
b1 *
1#
#65000
0#
#70000
b10 '
b10 *
1#
#75000
0#
0!
#80000
1#
#85000
0#
#90000
1#
#95000
0#
