74HC194/x74194.v
module x74194(
    CR,S,DSR,DSL,CP,D, Q
);

input CR, DSR, DSL, CP;
input [3:0]D;
input [1:0]S;
output reg [3:0]Q;

always @(posedge CP or negedge CR)
begin
if (~CR)
    Q <= 4'b1111;
else
    case (S)
        2'b00: Q <= D;
        2'b01: Q <= Q << 1;
        2'b10: Q <= Q >> 1;
        2'b11: Q <= 4'b0000;
    endcase
end

endmodule

74HC194/x74194_tb.v
//~ `New testbench
`timescale  1ns / 1ps
`include "x74194.v"
module tb_x74194;

// x74194 Inputs
reg   CR                                   = 0 ;
reg   DSR                                  = 0 ;
reg   DSL                                  = 0 ;
reg   CP                                   = 0 ;
reg   [3:0]  D                             = 0 ;
reg   [1:0]  S                             = 0 ;

// x74194 Outputs
wire  [3:0]  Q                             ;

x74194  u_x74194 (
    .CR                      ( CR         ),
    .DSR                     ( DSR        ),
    .DSL                     ( DSL        ),
    .CP                      ( CP         ),
    .D                       ( D    [3:0] ),
    .S                       ( S    [1:0] ),

    .Q                       ( Q    [3:0] )
);

initial
$monitor($time,"\tDSR=%b,DSL=%b,S=%b,D=%b,Q=%b",DSR,DSL,S,D,Q);
//时钟脉冲
initial 
	CP=0;
always
	#1 CP=~CP;
//测试
initial 
begin
    $dumpfile("x74194.vcd");
    $dumpvars(0,u_x74194,CR,DSR,DSL,CP,D,S,Q);
	//预置为1111
	CR=1;S=2'b11;DSR=0;DSL=0;D=4'b1111;
	#2
	//清零
	CR=0;S=2'b11;DSR=0;DSL=0;D=4'b1111;
	#2
	//右移，DSR=1
	CR=1;S=2'b01;DSR=1;DSL=0;D=4'b1111;
	#2
	//右移，DSR=1
	CR=1;S=2'b01;DSR=1;DSL=0;D=4'b1111;
	#2
	//右移，DSR=0
	CR=1;S=2'b01;DSR=0;DSL=0;D=4'b1111;
	#2
	//右移，DSR=0
	CR=1;S=2'b01;DSR=0;DSL=0;D=4'b1111;
	#2
	//清零
	CR=0;S=2'b11;DSR=0;DSL=0;D=4'b1111;
	#2
	//左移，DSL=1
	CR=1;S=2'b10;DSR=0;DSL=1;D=4'b1111;
	#2
	//左移，DSL=1
	CR=1;S=2'b10;DSR=0;DSL=1;D=4'b1111;
	#2
	//左移，DSL=0
	CR=1;S=2'b10;DSR=0;DSL=0;D=4'b1111;
	#2
	//左移，DSL=0
	CR=1;S=2'b10;DSR=0;DSL=0;D=4'b1111;
	#2
	$finish;
end

endmodule

74HC194/x74194.vcd
$date
	Wed Dec 20 21:05:48 2023
$end
$version
	Icarus Verilog
$end
$timescale
	1ps
$end
$scope module tb_x74194 $end
$scope module u_x74194 $end
$var wire 1 ! CP $end
$var wire 1 " CR $end
$var wire 4 # D [3:0] $end
$var wire 1 $ DSL $end
$var wire 1 % DSR $end
$var wire 2 & S [1:0] $end
$var reg 4 ' Q [3:0] $end
$upscope $end
$upscope $end
$scope module tb_x74194 $end
$var reg 1 " CR $end
$upscope $end
$scope module tb_x74194 $end
$var reg 1 % DSR $end
$upscope $end
$scope module tb_x74194 $end
$var reg 1 $ DSL $end
$upscope $end
$scope module tb_x74194 $end
$var reg 1 ! CP $end
$upscope $end
$scope module tb_x74194 $end
$var reg 4 ( D [3:0] $end
$upscope $end
$scope module tb_x74194 $end
$var reg 2 ) S [1:0] $end
$upscope $end
$scope module tb_x74194 $end
$var wire 4 * Q [3:0] $end
$upscope $end
$enddefinitions $end
$comment Show the parameter values. $end
$dumpall
$end
#0
$dumpvars
b0 *
b11 )
b1111 (
b0 '
b11 &
0%
0$
b1111 #
1"
0!
$end
#1000
1!
#2000
b1111 '
b1111 *
0!
0"
#3000
1!
#4000
0!
1%
b1 &
b1 )
1"
#5000
b1110 '
b1110 *
1!
#6000
0!
#7000
b1100 '
b1100 *
1!
#8000
0!
0%
#9000
b1000 '
b1000 *
1!
#10000
0!
#11000
b0 '
b0 *
1!
#12000
b1111 '
b1111 *
0!
b11 &
b11 )
0"
#13000
1!
#14000
0!
1$
b10 &
b10 )
1"
#15000
b111 '
b111 *
1!
#16000
0!
#17000
b11 '
b11 *
1!
#18000
0!
0$
#19000
b1 '
b1 *
1!
#20000
0!
#21000
b0 '
b0 *
1!
#22000
0!
