74HC138/x74138.v
module x74138(
    En,
    I,
    O
);
  input wire [2:0] En;  //使能端
  input wire [2:0] I;   //输入端
  output wire [7:0] O;  //输出端

  assign O = (En == 3'b100) ? ~(8'b0000_0001 << I) : ~(8'b0000_0000);
  //74HC138的逻辑实现，当使能端为100时，输出端为输入端的2^I次方，否则输出端为全1
endmodule

74HC138/x74138_tb.v
//~ `New testbench
`timescale  1ns / 1ps
`include "x74138.v"

module tb_x74138;

// x74138 Inputs
reg   [2:0]  En                            = 0 ;
reg   [2:0]  I                             = 0 ;

// x74138 Outputs
wire  [7:0]  O                             ;

x74138  u_x74138 (
    .En                      ( En  [2:0] ),
    .I                       ( I   [2:0] ),

    .O                       ( O   [7:0] )
);

initial
    $monitor($time,":\t En=%b, I=%b, O=%b\n", En, I, O);
initial
begin
    $dumpfile("x74138.vcd");
    $dumpvars(0, u_x74138, En, I, O);
    En=3'b010; I=3'b000;
    #1 
    En=3'b001; I=3'b000;
    #1 
    En=3'b000; I=3'b000;
    #1 
    En=3'b100; I=3'b000;
    #1 
    En=3'b100; I=3'b001;
    #1 
    En=3'b100; I=3'b010;
    #1 
    En=3'b100; I=3'b011;
    #1 
    En=3'b100; I=3'b100;
    #1 
    En=3'b100; I=3'b101;
    #1 
    En=3'b100; I=3'b110;
    #1 
    En=3'b100; I=3'b111;
    #1 
    $finish;
end

endmodule

74HC138/x74138.vcd
$date
	Tue Dec 19 21:46:54 2023
$end
$version
	Icarus Verilog
$end
$timescale
	1ps
$end
$scope module tb_x74138 $end
$scope module u_x74138 $end
$var wire 3 ! En [2:0] $end
$var wire 3 " I [2:0] $end
$var wire 8 # O [7:0] $end
$upscope $end
$upscope $end
$scope module tb_x74138 $end
$var reg 3 $ En [2:0] $end
$upscope $end
$scope module tb_x74138 $end
$var reg 3 % I [2:0] $end
$upscope $end
$scope module tb_x74138 $end
$var wire 8 & O [7:0] $end
$upscope $end
$enddefinitions $end
$comment Show the parameter values. $end
$dumpall
$end
#0
$dumpvars
b11111111 &
b0 %
b10 $
b11111111 #
b0 "
b10 !
$end
#1000
b1 !
b1 $
#2000
b0 !
b0 $
#3000
b11111110 #
b11111110 &
b100 !
b100 $
#4000
b11111101 #
b11111101 &
b1 "
b1 %
#5000
b11111011 #
b11111011 &
b10 "
b10 %
#6000
b11110111 #
b11110111 &
b11 "
b11 %
#7000
b11101111 #
b11101111 &
b100 "
b100 %
#8000
b11011111 #
b11011111 &
b101 "
b101 %
#9000
b10111111 #
b10111111 &
b110 "
b110 %
#10000
b1111111 #
b1111111 &
b111 "
b111 %
